<yml_catalog date="2023-03-06 15:55">
<shop>
<name>TeraFlops Store</name>
<url>https://tera-flops.com.ua/</url>
<currencies>
<currency id="USD" rate="41"/>
<currency id="UAH" rate="1"/>
</currencies>
<categories>
<category id="85328850">Комплектуючі для ПК</category>
<category id="85328986" parentId="85328850">Відеокарти</category>
<category id="85364244" parentId="85328850">Материнські плати</category>
</categories>
<offers>
<offer id="1641488880" available="true">
<url>https://tera-flops.com.ua/ua/p1641488880-videokarta-amd-radeon.html</url>
<price>17100</price>
<currencyId>UAH</currencyId>
<categoryId>85328986</categoryId>
<picture>https://microtron.ua/image/cache/catalog/products/p230730-8762-700x700.png</picture>
<pickup>true</pickup>
<delivery>true</delivery>
<name>Відеокарта AMD Radeon RX 6600 XT 8GB GIGABYTE GAMING OC PRO (GV-R66XTGAMINGOC PRO-8GD)</name>
<vendor>Gigabyte</vendor>
<vendorCode>GV-R66XTGAMINGOC PRO-8GD</vendorCode>
<guarantee type="shop">24 міс</guarantee>
</offer>
<offer id="1641921246" available="true">
<url>https://tera-flops.com.ua/ua/p1641921246-videokarta-gtx-1660.html</url>
<price>12530</price>
<currencyId>UAH</currencyId>
<categoryId>85328986</categoryId>
<picture>https://img.moyo.ua/img/products/5261/54_1500.jpg?1675176945</picture>
<pickup>true</pickup>
<delivery>true</delivery>
<name>Відеокарта GTX 1660 SUPER 6GB ASUS TUF Gaming (TUF-GTX1660S-O6G-GAMING)</name>
<vendor>Asus</vendor>
<vendorCode>TUF-GTX1660S-O6G-GAMING</vendorCode>
<guarantee type="shop">24 міс</guarantee>
</offer>
<offer id="1641935012" available="true">
<url>https://tera-flops.com.ua/ua/p1641935012-videokarta-amd-radeon.html</url>
<price>13720</price>
<currencyId>UAH</currencyId>
<categoryId>85328986</categoryId>
<picture>https://content.rozetka.com.ua/goods/images/big/234117497.jpg</picture>
<pickup>true</pickup>
<delivery>true</delivery>
<name>Відеокарта AMD Radeon RX 6600 8GB ASUS DUAL (DUAL-RX6600-8G)</name>
<vendor>Asus</vendor>
<vendorCode>DUAL-RX6600-8G</vendorCode>
<guarantee type="shop">24 міс</guarantee>
</offer>
<offer id="1672986238" available="true">
<url>https://tera-flops.com.ua/ua/p1672986238-videokarta-gigabyte-nvidia.html</url>
<price>30930</price>
<currencyId>UAH</currencyId>
<categoryId>85328986</categoryId>
<picture>https://content2.rozetka.com.ua/goods/images/big/288136584.jpg</picture>
<pickup>true</pickup>
<delivery>true</delivery>
<name>Відеокарта GIGABYTE nVIDIA RTX 3070TI 8GB DDR6X (GV-N307TEAGLE OC-8GD)</name>
<vendor>Gigabyte</vendor>
<vendorCode>GV-N307TEAGLE OC-8GD</vendorCode>
<guarantee type="shop">24 міс</guarantee>
</offer>
<offer id="1673038571" available="true">
<url>https://tera-flops.com.ua/ua/p1673038571-videokarta-palit-rtx3070ti.html</url>
<price>29230</price>
<currencyId>UAH</currencyId>
<categoryId>85328986</categoryId>
<picture>https://hotline.ua/img/tx/282/2826300775.jpg</picture>
<pickup>true</pickup>
<delivery>true</delivery>
<name>Відеокарта PALIT RTX3070Ti GAMEROCK OC 8GB (NED307T19P2-1047G)</name>
<vendor>Palit</vendor>
<vendorCode>NED307TT19P2-1047G</vendorCode>
<guarantee type="shop">24 міс</guarantee>
</offer>
<offer id="1676329396" available="true">
<url>https://tera-flops.com.ua/ua/p1676329396-videokarta-amd-radeon.html</url>
<price>7850</price>
<currencyId>UAH</currencyId>
<categoryId>85328986</categoryId>
<picture>https://content2.rozetka.com.ua/goods/images/big/284413330.jpg</picture>
<pickup>true</pickup>
<delivery>true</delivery>
<name>Відеокарта AMD Radeon RX 6500 XT 4GB PowerColor Fighter (AXRX 6500XT 4GBD6-DH/OC)</name>
<vendor>PowerColor</vendor>
<vendorCode>AXRX 6500XT 4GBD6-DH/OC</vendorCode>
<guarantee type="shop">24 міс</guarantee>
</offer>
<offer id="1688927971" available="true">
<url>https://tera-flops.com.ua/ua/p1688927971-videokarta-rtx-3060.html</url>
<price>18520</price>
<currencyId>UAH</currencyId>
<categoryId>85328986</categoryId>
<picture>https://proton-it.kyiv.ua/content/images/32/480x480l50nn0/34679752796517.png</picture>
<pickup>true</pickup>
<delivery>true</delivery>
<name>Відеокарта RTX 3060 8GB MSI Ventus (912-V397-051)</name>
<vendor>MSI</vendor>
<vendorCode>912-V397-051</vendorCode>
<guarantee type="shop">24 міс</guarantee>
</offer>
<offer id="1688945808" available="true">
<url>https://tera-flops.com.ua/ua/p1688945808-videokarta-rtx-3060.html</url>
<price>17300</price>
<currencyId>UAH</currencyId>
<categoryId>85328986</categoryId>
<picture>https://content2.rozetka.com.ua/goods/images/big/292642936.jpg</picture>
<pickup>true</pickup>
<delivery>true</delivery>
<name>Відеокарта RTX 3060 12GB GIGABYTE (GV-N3060WF2OC-12GD)</name>
<vendor>Gigabyte</vendor>
<vendorCode>GV-N3060WF2OC-12GD</vendorCode>
<guarantee type="shop">24 міс</guarantee>
</offer>
<offer id="1688962126" available="true">
<url>https://tera-flops.com.ua/ua/p1688962126-videokarta-rtx-3060.html</url>
<price>20270</price>
<currencyId>UAH</currencyId>
<categoryId>85328986</categoryId>
<picture>https://hotline.ua/img/tx/244/2442548795.jpg</picture>
<pickup>true</pickup>
<delivery>true</delivery>
<name>Відеокарта RTX 3060 Ti 8GB Palit Dual (NE6306T019P2-190AD)</name>
<vendor>Palit</vendor>
<vendorCode>NE6306T019P2-190AD</vendorCode>
<guarantee type="shop">24 міс</guarantee>
</offer>
<offer id="1689025717" available="true">
<url>https://tera-flops.com.ua/ua/p1689025717-videokarta-rtx-3070.html</url>
<price>32480</price>
<currencyId>UAH</currencyId>
<categoryId>85328986</categoryId>
<picture>https://static-media.laptopoutlet.co.uk/catalog/product/9/3/93809272_5547942892.jpg?store=default&image-type=image</picture>
<pickup>true</pickup>
<delivery>true</delivery>
<name>Відеокарта RTX 3070 Ti 8GB MSI Gaming X Trio (912-V505-011)</name>
<vendor>MSI</vendor>
<vendorCode>912-V505-011</vendorCode>
<guarantee type="shop">24 міс</guarantee>
</offer>
<offer id="1641506541" available="true">
<url>https://tera-flops.com.ua/ua/p1641506541-videokarta-amd-radeon.html</url>
<price>19890</price>
<currencyId>UAH</currencyId>
<categoryId>85328986</categoryId>
<picture>https://www.gigabyte.com/FileUpload/Global/KeyFeature/1763/innergigabyteimages/kf-img.png</picture>
<pickup>true</pickup>
<delivery>true</delivery>
<name>Відеокарта AMD Radeon RX 6700 XT 12GB GIGABYTE EAGLE (GV-R67XTEAGLE-12GD)</name>
<vendor>Gigabyte</vendor>
<vendorCode>GV-R67XTEAGLE-12GD</vendorCode>
<guarantee type="shop">24 міс</guarantee>
</offer>
<offer id="1671212957" available="true">
<url>https://tera-flops.com.ua/ua/p1671212957-videokarta-rtx-3090.html</url>
<price>42150</price>
<currencyId>UAH</currencyId>
<categoryId>85328986</categoryId>
<picture>https://www.manli.com/upload/2020/11/03/s[1]_1nx5fez0sdgbr1604381965.png</picture>
<pickup>true</pickup>
<delivery>true</delivery>
<name>Відеокарта RTX 3090 24GB Manli (M-NRTX3090/6RHHPPP-M3478)</name>
<vendor>Manli</vendor>
<vendorCode>M-NRTX3090/6RHHPPP-M3478</vendorCode>
<guarantee type="shop">24 міс</guarantee>
</offer>
<offer id="1676336303" available="true">
<url>https://tera-flops.com.ua/ua/p1676336303-videokarta-rtx-3060.html</url>
<price>16750</price>
<currencyId>UAH</currencyId>
<categoryId>85328986</categoryId>
<picture>https://content.rozetka.com.ua/goods/images/big/244885518.jpg</picture>
<pickup>true</pickup>
<delivery>true</delivery>
<name>Відеокарта RTX 3060 Ti 8GB PNY REVEL EPIC-X RGB (VCG3060T8LDFXPPB)</name>
<vendor>PNY</vendor>
<vendorCode>VCG3060T8LDFXPPB</vendorCode>
<guarantee type="shop">24 міс</guarantee>
</offer>
<offer id="1688516285" available="true">
<url>https://tera-flops.com.ua/ua/p1688516285-videokarta-rtx-3070.html</url>
<price>28360</price>
<currencyId>UAH</currencyId>
<categoryId>85328986</categoryId>
<picture>https://hotline.ua/img/tx/286/2867428785.jpg</picture>
<pickup>true</pickup>
<delivery>true</delivery>
<name>Відеокарта RTX 3070 8GB GIGABYTE AORUS MASTER (GV-N3070AORUS M-8GD)</name>
<vendor>Gigabyte</vendor>
<vendorCode>GV-N3070AORUS M-8GD</vendorCode>
<guarantee type="shop">24 міс</guarantee>
</offer>
<offer id="1688940558" available="true">
<url>https://tera-flops.com.ua/ua/p1688940558-videokarta-rtx-3060.html</url>
<price>20150</price>
<currencyId>UAH</currencyId>
<categoryId>85328986</categoryId>
<picture>https://img.moyo.ua/img/gallery/5235/44/1553042_middle.jpg?1676879021</picture>
<pickup>true</pickup>
<delivery>true</delivery>
<name>Відеокарта RTX 3060 12GB MSI GAMING Z TRIO (912-V390-255)</name>
<vendor>MSI</vendor>
<vendorCode>912-V390-255</vendorCode>
<guarantee type="shop">24 міс</guarantee>
</offer>
<offer id="1688969917" available="true">
<url>https://tera-flops.com.ua/ua/p1688969917-videokarta-rtx-3060.html</url>
<price>19450</price>
<currencyId>UAH</currencyId>
<categoryId>85328986</categoryId>
<picture>https://www.inno3d.com/assets/files/product_image/image/3060TiX2_set_v2.png</picture>
<pickup>true</pickup>
<delivery>true</delivery>
<name>Відеокарта RTX 3060 TI 8GB Inno3D Twin X2 (N306T2-08D6X-119032)</name>
<vendor>Inno3D</vendor>
<vendorCode>N306T2-08D6X-119032</vendorCode>
<guarantee type="shop">24 міс</guarantee>
</offer>
<offer id="1727180649" available="true">
<url>https://tera-flops.com.ua/ua/p1727180649-videokarta-rtx-3060.html</url>
<price>18000</price>
<currencyId>UAH</currencyId>
<categoryId>85328986</categoryId>
<picture>https://dlcdnwebimgs.asus.com/gain/e4ae0c15-6bd8-482b-aa5b-47506dff16fc/</picture>
<pickup>true</pickup>
<delivery>true</delivery>
<name>Відеокарта RTX 3060 Ti 8GB Asus Dual Mini (DUAL-RTX30TI-8G-MINI-V2)</name>
<vendor>Asus</vendor>
<vendorCode>DUAL-RTX3060TI-8G-MINI-V2</vendorCode>
<guarantee type="shop">24 міс</guarantee>
</offer>
<offer id="1776733579" available="true">
<url>https://tera-flops.com.ua/ua/p1776733579-videokarta-rtx-3080.html</url>
<price>30820</price>
<currencyId>UAH</currencyId>
<categoryId>85328986</categoryId>
<picture>https://gzhls.at/i/42/88/2664288-n0.jpg</picture>
<pickup>true</pickup>
<delivery>true</delivery>
<name>Відеокарта RTX 3080 10GB Palit GAMINGPRO (NED3080019IA-132AA)</name>
<vendor>Palit</vendor>
<vendorCode>NED3080019IA-132AA</vendorCode>
<guarantee type="shop">24 міс</guarantee>
</offer>
<offer id="1641745560" available="true">
<url>https://tera-flops.com.ua/ua/p1641745560-materinska-plata-msi.html</url>
<price>4580</price>
<currencyId>UAH</currencyId>
<categoryId>85364244</categoryId>
<picture>https://content.rozetka.com.ua/goods/images/big/247626965.png</picture>
<pickup>true</pickup>
<delivery>true</delivery>
<name>Материнська плата MSI PRO B660M-G DDR4 1700 (PRO B660M-G DDR4)</name>
<vendor>MSI</vendor>
<vendorCode>PRO B660M-G DDR4</vendorCode>
<guarantee type="shop">24 міс</guarantee>
</offer>
<offer id="1673510567" available="true">
<url>https://tera-flops.com.ua/ua/p1673510567-materinska-plata-gigabyte.html</url>
<price>3980</price>
<currencyId>UAH</currencyId>
<categoryId>85364244</categoryId>
<picture>https://content.rozetka.com.ua/goods/images/big/56496588.jpg</picture>
<pickup>true</pickup>
<delivery>true</delivery>
<name>Материнська плата GIGABYTE B450 AORUS ELITE V2 (B450 AORUS ELITE V2)</name>
<vendor>Gigabyte</vendor>
<vendorCode>B450 AORUS ELITE V2</vendorCode>
<guarantee type="shop">24 міс</guarantee>
</offer>
<offer id="1673512466" available="true">
<url>https://tera-flops.com.ua/ua/p1673512466-materinska-plata-gigabyte.html</url>
<price>5010</price>
<currencyId>UAH</currencyId>
<categoryId>85364244</categoryId>
<picture>https://content2.rozetka.com.ua/goods/images/big/121207676.png</picture>
<pickup>true</pickup>
<delivery>true</delivery>
<name>Материнська плата GIGABYTE B550 GAMING X V2 (B550 GAMING X V2)</name>
<vendor>Gigabyte</vendor>
<vendorCode>B550 GAMING X V2</vendorCode>
<guarantee type="shop">24 міс</guarantee>
</offer>
<offer id="1673524644" available="true">
<url>https://tera-flops.com.ua/ua/p1673524644-materinska-plata-gigabyte.html</url>
<price>6060</price>
<currencyId>UAH</currencyId>
<categoryId>85364244</categoryId>
<picture>https://content1.rozetka.com.ua/goods/images/big/180835076.jpg</picture>
<pickup>true</pickup>
<delivery>true</delivery>
<name>Материнська плата GIGABYTE B550 AORUS ELITE V2 (B550 AORUS ELITE V2)</name>
<vendor>Gigabyte</vendor>
<vendorCode>B550 AORUS ELITE V2</vendorCode>
<guarantee type="shop">24 міс</guarantee>
</offer>
<offer id="1673529257" available="true">
<url>https://tera-flops.com.ua/ua/p1673529257-materinska-plata-gigabyte.html</url>
<price>5700</price>
<currencyId>UAH</currencyId>
<categoryId>85364244</categoryId>
<picture>https://content1.rozetka.com.ua/goods/images/big/271257750.jpg</picture>
<pickup>true</pickup>
<delivery>true</delivery>
<name>Материнська плата GIGABYTE B660M GAMING X DDR4 (B660M GAMING X DDR4)</name>
<vendor>Gigabyte</vendor>
<vendorCode>B660M GAMING X DDR4</vendorCode>
<guarantee type="shop">24 міс</guarantee>
</offer>
<offer id="1683806132" available="true">
<url>https://tera-flops.com.ua/ua/p1683806132-materinska-plata-asrock.html</url>
<price>2490</price>
<currencyId>UAH</currencyId>
<categoryId>85364244</categoryId>
<picture>https://photo.kvshop.com.ua/products/187/187394/asrock-h510m-hdv-r2-0.o.jpg</picture>
<pickup>true</pickup>
<delivery>true</delivery>
<name>Материнська плата ASRock H510M-HDV R2.0 Socket 1200 (H510M-HDV R2.0)</name>
<vendor>ASRock</vendor>
<vendorCode>H510M-HDV R2.0</vendorCode>
<guarantee type="shop">24 міс</guarantee>
</offer>
<offer id="1684881581" available="true">
<url>https://tera-flops.com.ua/ua/p1684881581-materinskaya-plata-asus.html</url>
<price>4190</price>
<currencyId>UAH</currencyId>
<categoryId>85364244</categoryId>
<picture>https://content2.rozetka.com.ua/goods/images/big/246380538.jpg</picture>
<pickup>true</pickup>
<delivery>true</delivery>
<name>Материнская плата Asus Prime H610M-A D4 Socket 1700 (PRIME H610M-A D4)</name>
<vendor>Asus</vendor>
<vendorCode>PRIME H610M-A D4</vendorCode>
<guarantee type="shop">24 міс</guarantee>
</offer>
<offer id="1711254865" available="true">
<url>https://tera-flops.com.ua/ua/p1711254865-materinska-plata-colorful.html</url>
<price>3150</price>
<currencyId>UAH</currencyId>
<categoryId>85364244</categoryId>
<picture>https://i.can.ua/images/700x700/goods/10609/10609033.jpg</picture>
<pickup>true</pickup>
<delivery>true</delivery>
<name>Материнська плата Colorful H610M-D M.2 V20 LGA 1700 (H610M-D M.2 V20)</name>
<vendor>Colorful</vendor>
<vendorCode>H610M-D M.2 V20</vendorCode>
<guarantee type="shop">24 міс</guarantee>
</offer>
<offer id="1734386251" available="true">
<url>https://tera-flops.com.ua/ua/p1734386251-materinska-plata-asus.html</url>
<price>2740</price>
<currencyId>UAH</currencyId>
<categoryId>85364244</categoryId>
<picture>https://content.rozetka.com.ua/goods/images/big/180575730.jpg</picture>
<pickup>true</pickup>
<delivery>true</delivery>
<name>Материнська плата ASUS PRIME H510M-K Socket 1200 (PRIME H510M-K)</name>
<vendor>Asus</vendor>
<vendorCode>PRIME H510M-K</vendorCode>
<guarantee type="shop">24 міс</guarantee>
</offer>
<offer id="1734974166" available="true">
<url>https://tera-flops.com.ua/ua/p1734974166-materinska-plata-asus.html</url>
<price>2860</price>
<currencyId>UAH</currencyId>
<categoryId>85364244</categoryId>
<picture>https://content2.rozetka.com.ua/goods/images/big/267410865.jpg</picture>
<pickup>true</pickup>
<delivery>true</delivery>
<name>Материнська плата Asus Prime H510M-R-SI Socket 1200 (PRIME H510M-R-SI)</name>
<vendor>Asus</vendor>
<vendorCode>PRIME H510M-R-SI</vendorCode>
<guarantee type="shop">24 міс</guarantee>
</offer>
<offer id="1766109763" available="true">
<url>https://tera-flops.com.ua/ua/p1766109763-materinska-plata-asrock.html</url>
<price>2500</price>
<currencyId>UAH</currencyId>
<categoryId>85364244</categoryId>
<picture>https://www.asrock.com/mb/photo/H470M-HDV(M1).png</picture>
<pickup>true</pickup>
<delivery>true</delivery>
<name>Материнська плата ASRock H470M-HDV LGA 1200 (H470M-HDV)</name>
<vendor>ASRock</vendor>
<vendorCode>H470M-HDV</vendorCode>
<guarantee type="shop">24 міс</guarantee>
</offer>
</offers>
</shop>
</yml_catalog>
